{
    "providers": {
        "awscloudformation": {
            "AuthRoleName": "amplify-amplifydatasource-awsp-190404-authRole",
            "UnauthRoleArn": "arn:aws:iam::479545181301:role/amplify-amplifydatasource-awsp-190404-unauthRole",
            "AuthRoleArn": "arn:aws:iam::479545181301:role/amplify-amplifydatasource-awsp-190404-authRole",
            "Region": "us-east-2",
            "DeploymentBucketName": "amplify-amplifydatasource-awsp-190404-deployment",
            "UnauthRoleName": "amplify-amplifydatasource-awsp-190404-unauthRole",
            "StackName": "amplify-amplifydatasource-awsp-190404",
            "StackId": "arn:aws:cloudformation:us-east-2:479545181301:stack/amplify-amplifydatasource-awsp-190404/6a6be480-7f6d-11ea-bb55-06f0515d2d5c",
            "AmplifyAppId": "d2rdze2ztwhfx8"
        }
    },
    "api": {
        "amplifyDatasource-amplify": {
            "service": "AppSync",
            "output": {
                "authConfig": {
                    "defaultAuthentication": {
                        "authenticationType": "API_KEY"
                    },
                    "additionalAuthenticationProviders": null
                },
                "GraphQLAPIIdOutput": "el56uyhckffnncwngcds7jhyie",
                "GraphQLAPIEndpointOutput": "https://ianjndvuazebzjs2eto5hysfyy.appsync-api.us-east-1.amazonaws.com/graphql",
                "name": "amplifyDatasource-amplify",
                "region": "us-east-1",
                "GraphQLAPIKeyOutput": "da2-nzk44lbxprfr3i2unt42xwbb3y"
            },
            "lastPushTimeStamp": "2020-04-16T06:00:05.120Z"
        }
    }
}